{
  "generator-jhipster": {
    "promptValues": {
      "packageName": "com.awabcodes.smartcommunity",
      "nativeLanguage": "en"
    },
    "jhipsterVersion": "6.10.5",
    "applicationType": "monolith",
    "baseName": "smartcommunity",
    "packageName": "com.awabcodes.smartcommunity",
    "packageFolder": "com/awabcodes/smartcommunity",
    "serverPort": "8080",
    "authenticationType": "jwt",
    "cacheProvider": "ehcache",
    "enableHibernateCache": true,
    "websocket": false,
    "databaseType": "sql",
    "devDatabaseType": "mysql",
    "prodDatabaseType": "mysql",
    "searchEngine": false,
    "messageBroker": false,
    "serviceDiscoveryType": false,
    "buildTool": "maven",
    "enableSwaggerCodegen": false,
    "jwtSecretKey": "NTRiODFlYTcyMzk2NTBhMGU0MGJhM2NlODY3MzgyZmNiNDg3MTk1ZDlkOTQ0NmRkODdkOWQwYmIzZGUyOWZlYzE5OGM3NjhiZWMzNTMwZTFhNTJmNmExOTAyN2JlZGI0MDcwYjA2YTE4MTA3NmZmNGU1OGUxZTZkNTNhZjgwZjg=",
    "embeddableLaunchScript": false,
    "useSass": true,
    "clientPackageManager": "npm",
    "clientFramework": "angularX",
    "clientTheme": "lux",
    "clientThemeVariant": "primary",
    "creationTimestamp": 1605804922310,
    "testFrameworks": [],
    "jhiPrefix": "jhi",
    "entitySuffix": "",
    "dtoSuffix": "DTO",
    "otherModules": [],
    "enableTranslation": true,
    "nativeLanguage": "en",
    "languages": ["en", "ar-ly"],
    "blueprints": []
  }
}
